QTvisualiser/__init__.py
QTvisualiser/__main__.py
QTvisualiser/app.py
QTvisualiser/controllers.py
QTvisualiser/form.ui
QTvisualiser/models.py
QTvisualiser/second_app.ui
QTvisualiser/views.py
slaven92_QTvisualiser-1.1.2.dist-info/METADATA
slaven92_QTvisualiser-1.1.2.dist-info/WHEEL
slaven92_QTvisualiser-1.1.2.dist-info/entry_points.txt
slaven92_QTvisualiser-1.1.2.dist-info/top_level.txt
slaven92_QTvisualiser-1.1.2.dist-info/RECORD
