Metadata-Version: 2.1
Name: slaven92-QTvisualiser
Version: 1.1.2
Summary: Visualise cross section of a 3D image
Home-page: https://github.com/slaven92/QTvisualiser
Author: Slaven Tepsic
Author-email: slaven.tepsic@icfo.eu
License: MIT
Platform: UNKNOWN
Classifier: License :: OSI Approved :: MIT License
Classifier: Programming Language :: Python :: 3
Classifier: Programming Language :: Python :: 3.8
Requires-Dist: PyQt5
Requires-Dist: pyqtgraph
